safe_password.py
example_safe_password/__init__.py
example_safe_password/example.py
example_safe_password/sql-example.py
safe_password-1.0.dist-info/LICENSE
safe_password-1.0.dist-info/METADATA
safe_password-1.0.dist-info/WHEEL
safe_password-1.0.dist-info/top_level.txt
safe_password-1.0.dist-info/RECORD
