Metadata-Version: 2.1
Name: safe-password
Version: 1.0
Summary: A very simple library to safe your passwords.
Author-email: daniel5551 <danielafanasev@disroot.org>
License: GNU GENERAL PUBLIC LICENSE
Project-URL: Homepage, https://github.com/daniel5551/safe_password
Project-URL: Issues, https://github.com/daniel5551/safe_password/issues
Keywords: password,hashing,security,salt
Classifier: Programming Language :: Python :: 3
Classifier: License :: OSI Approved :: GNU Affero General Public License v3 or later (AGPLv3+)
Classifier: Operating System :: OS Independent
Requires-Python: >=3.8
License-File: LICENSE
